{
"meta":{"test_sets":[],"test_metrics":[],"learn_metrics":[{"best_value":"Min","name":"Logloss"}],"launch_mode":"Train","parameters":"","iteration_count":300,"learn_sets":["learn"],"name":"experiment"},
"iterations":[
{"learn":[0.6677137381],"iteration":0,"passed_time":0.07859013611,"remaining_time":23.4984507},
{"learn":[0.6445402229],"iteration":1,"passed_time":0.1460287663,"remaining_time":21.75828618},
{"learn":[0.626694957],"iteration":2,"passed_time":0.2245685551,"remaining_time":22.23228695},
{"learn":[0.6100949125],"iteration":3,"passed_time":0.2948179088,"remaining_time":21.81652525},
{"learn":[0.5953568615],"iteration":4,"passed_time":0.375815548,"remaining_time":22.17311733},
{"learn":[0.5801056671],"iteration":5,"passed_time":0.4540800847,"remaining_time":22.24992415},
{"learn":[0.5683551129],"iteration":6,"passed_time":0.5261161292,"remaining_time":22.02171798},
{"learn":[0.5576296206],"iteration":7,"passed_time":0.6008295538,"remaining_time":21.93027872},
{"learn":[0.5468521258],"iteration":8,"passed_time":0.6844263873,"remaining_time":22.12978652},
{"learn":[0.539648077],"iteration":9,"passed_time":0.752786277,"remaining_time":21.83080203},
{"learn":[0.5315574981],"iteration":10,"passed_time":0.8283946677,"remaining_time":21.76418718},
{"learn":[0.5247270135],"iteration":11,"passed_time":0.9049896151,"remaining_time":21.71975076},
{"learn":[0.5189724876],"iteration":12,"passed_time":0.9838260859,"remaining_time":21.71985282},
{"learn":[0.5138416052],"iteration":13,"passed_time":1.052627802,"remaining_time":21.50368224},
{"learn":[0.5079221317],"iteration":14,"passed_time":1.132369884,"remaining_time":21.51502779},
{"learn":[0.5034935503],"iteration":15,"passed_time":1.210381825,"remaining_time":21.48427739},
{"learn":[0.4989710118],"iteration":16,"passed_time":1.300742455,"remaining_time":21.65353616},
{"learn":[0.4938273505],"iteration":17,"passed_time":1.372478227,"remaining_time":21.50215888},
{"learn":[0.490060596],"iteration":18,"passed_time":1.449732393,"remaining_time":21.44077908},
{"learn":[0.486693105],"iteration":19,"passed_time":1.527395091,"remaining_time":21.38353128},
{"learn":[0.4832272571],"iteration":20,"passed_time":1.615979714,"remaining_time":21.46944478},
{"learn":[0.4800607117],"iteration":21,"passed_time":1.7023164,"remaining_time":21.51108906},
{"learn":[0.4766457478],"iteration":22,"passed_time":1.773586005,"remaining_time":21.36014449},
{"learn":[0.4741328968],"iteration":23,"passed_time":1.875072129,"remaining_time":21.56332948},
{"learn":[0.471538783],"iteration":24,"passed_time":1.955572599,"remaining_time":21.51129859},
{"learn":[0.469135459],"iteration":25,"passed_time":2.039630088,"remaining_time":21.49456323},
{"learn":[0.466610417],"iteration":26,"passed_time":2.132434767,"remaining_time":21.56128487},
{"learn":[0.4645600814],"iteration":27,"passed_time":2.212456105,"remaining_time":21.49243074},
{"learn":[0.4624017712],"iteration":28,"passed_time":2.28241724,"remaining_time":21.32879559},
{"learn":[0.4602489612],"iteration":29,"passed_time":2.377238848,"remaining_time":21.39514963},
{"learn":[0.4584698853],"iteration":30,"passed_time":2.46442788,"remaining_time":21.38487418},
{"learn":[0.4565238238],"iteration":31,"passed_time":2.549122717,"remaining_time":21.34890276},
{"learn":[0.4551308563],"iteration":32,"passed_time":2.627177113,"remaining_time":21.25625119},
{"learn":[0.4537024861],"iteration":33,"passed_time":2.703872914,"remaining_time":21.15382927},
{"learn":[0.4521964475],"iteration":34,"passed_time":2.787661705,"remaining_time":21.10658148},
{"learn":[0.4510406519],"iteration":35,"passed_time":2.859967766,"remaining_time":20.97309695},
{"learn":[0.4497817014],"iteration":36,"passed_time":2.922805614,"remaining_time":20.77561828},
{"learn":[0.4485716469],"iteration":37,"passed_time":3.015936861,"remaining_time":20.79409099},
{"learn":[0.4471747277],"iteration":38,"passed_time":3.101971925,"remaining_time":20.75935058},
{"learn":[0.44586373],"iteration":39,"passed_time":3.186381614,"remaining_time":20.71148049},
{"learn":[0.4450345394],"iteration":40,"passed_time":3.252841516,"remaining_time":20.54843787},
{"learn":[0.444150695],"iteration":41,"passed_time":3.327150764,"remaining_time":20.43821184},
{"learn":[0.4429589392],"iteration":42,"passed_time":3.398726203,"remaining_time":20.31331708},
{"learn":[0.4419930112],"iteration":43,"passed_time":3.480464023,"remaining_time":20.2499725},
{"learn":[0.4411634051],"iteration":44,"passed_time":3.566444686,"remaining_time":20.20985322},
{"learn":[0.4401787385],"iteration":45,"passed_time":3.643054261,"remaining_time":20.11599527},
{"learn":[0.4393959255],"iteration":46,"passed_time":3.733901363,"remaining_time":20.09951159},
{"learn":[0.438154735],"iteration":47,"passed_time":3.818278671,"remaining_time":20.04596302},
{"learn":[0.4374608973],"iteration":48,"passed_time":3.907994084,"remaining_time":20.01850031},
{"learn":[0.4367639274],"iteration":49,"passed_time":3.989968913,"remaining_time":19.94984456},
{"learn":[0.4359869188],"iteration":50,"passed_time":4.07008791,"remaining_time":19.87160568},
{"learn":[0.4352037992],"iteration":51,"passed_time":4.14968989,"remaining_time":19.79082871},
{"learn":[0.4344089299],"iteration":52,"passed_time":4.21848174,"remaining_time":19.65971679},
{"learn":[0.4335299818],"iteration":53,"passed_time":4.303827661,"remaining_time":19.60632601},
{"learn":[0.4322967386],"iteration":54,"passed_time":4.396789916,"remaining_time":19.58570054},
{"learn":[0.4316313044],"iteration":55,"passed_time":4.472882085,"remaining_time":19.48898623},
{"learn":[0.4308366545],"iteration":56,"passed_time":4.543347381,"remaining_time":19.36900725},
{"learn":[0.4300479932],"iteration":57,"passed_time":4.621655039,"remaining_time":19.28345723},
{"learn":[0.4292411137],"iteration":58,"passed_time":4.697794862,"remaining_time":19.18929766},
{"learn":[0.4283687027],"iteration":59,"passed_time":4.791660541,"remaining_time":19.16664216},
{"learn":[0.4278260798],"iteration":60,"passed_time":4.863165208,"remaining_time":19.05404073},
{"learn":[0.4270096944],"iteration":61,"passed_time":4.934716922,"remaining_time":18.9429456},
{"learn":[0.4263755152],"iteration":62,"passed_time":5.020661836,"remaining_time":18.88725167},
{"learn":[0.4257249582],"iteration":63,"passed_time":5.099721312,"remaining_time":18.80522234},
{"learn":[0.4249823774],"iteration":64,"passed_time":5.183167714,"remaining_time":18.73914481},
{"learn":[0.4241822244],"iteration":65,"passed_time":5.2597707,"remaining_time":18.64827794},
{"learn":[0.423499778],"iteration":66,"passed_time":5.343471313,"remaining_time":18.58251964},
{"learn":[0.4226048667],"iteration":67,"passed_time":5.421788526,"remaining_time":18.49786674},
{"learn":[0.4219587457],"iteration":68,"passed_time":5.490529648,"remaining_time":18.38133839},
{"learn":[0.421233191],"iteration":69,"passed_time":5.573722404,"remaining_time":18.31365933},
{"learn":[0.4204695532],"iteration":70,"passed_time":5.659406818,"remaining_time":18.25357974},
{"learn":[0.4198827537],"iteration":71,"passed_time":5.727099115,"remaining_time":18.13581386},
{"learn":[0.4193384767],"iteration":72,"passed_time":5.794013307,"remaining_time":18.01700028},
{"learn":[0.4187627163],"iteration":73,"passed_time":5.87089983,"remaining_time":17.93004543},
{"learn":[0.4181216007],"iteration":74,"passed_time":5.951629891,"remaining_time":17.85488967},
{"learn":[0.4176915872],"iteration":75,"passed_time":6.024613172,"remaining_time":17.75675461},
{"learn":[0.4168644448],"iteration":76,"passed_time":6.117418981,"remaining_time":17.71668094},
{"learn":[0.4164195872],"iteration":77,"passed_time":6.193928231,"remaining_time":17.62887266},
{"learn":[0.4159389524],"iteration":78,"passed_time":6.279415085,"remaining_time":17.56646499},
{"learn":[0.4153824086],"iteration":79,"passed_time":6.358941046,"remaining_time":17.48708788},
{"learn":[0.4147856926],"iteration":80,"passed_time":6.434589529,"remaining_time":17.39722354},
{"learn":[0.4142851562],"iteration":81,"passed_time":6.502721685,"remaining_time":17.2877235},
{"learn":[0.4139658039],"iteration":82,"passed_time":6.597920273,"remaining_time":17.24998433},
{"learn":[0.4134317958],"iteration":83,"passed_time":6.689065004,"remaining_time":17.20045287},
{"learn":[0.4130015389],"iteration":84,"passed_time":6.766608538,"remaining_time":17.11553924},
{"learn":[0.4125155714],"iteration":85,"passed_time":6.846427652,"remaining_time":17.03645951},
{"learn":[0.4118604968],"iteration":86,"passed_time":6.91869471,"remaining_time":16.93887326},
{"learn":[0.4113295998],"iteration":87,"passed_time":6.995769213,"remaining_time":16.85344401},
{"learn":[0.4104705706],"iteration":88,"passed_time":7.070225711,"remaining_time":16.76199579},
{"learn":[0.4097727757],"iteration":89,"passed_time":7.15862089,"remaining_time":16.70344874},
{"learn":[0.4091915935],"iteration":90,"passed_time":7.234519854,"remaining_time":16.6155456},
{"learn":[0.4087346664],"iteration":91,"passed_time":7.299251556,"remaining_time":16.50265569},
{"learn":[0.4081458161],"iteration":92,"passed_time":7.372093617,"remaining_time":16.40885353},
{"learn":[0.4077735495],"iteration":93,"passed_time":7.448206234,"remaining_time":16.32266473},
{"learn":[0.4072444648],"iteration":94,"passed_time":7.518626293,"remaining_time":16.22440411},
{"learn":[0.40669764],"iteration":95,"passed_time":7.595112053,"remaining_time":16.13961311},
{"learn":[0.406071236],"iteration":96,"passed_time":7.670460082,"remaining_time":16.05261234},
{"learn":[0.405753687],"iteration":97,"passed_time":7.75757431,"remaining_time":15.99010215},
{"learn":[0.4051107341],"iteration":98,"passed_time":7.831022925,"remaining_time":15.89934957},
{"learn":[0.4048586272],"iteration":99,"passed_time":7.907026006,"remaining_time":15.81405201},
{"learn":[0.4045469294],"iteration":100,"passed_time":7.985112895,"remaining_time":15.73304422},
{"learn":[0.404220625],"iteration":101,"passed_time":8.06631023,"remaining_time":15.65813162},
{"learn":[0.4037361883],"iteration":102,"passed_time":8.150670196,"remaining_time":15.58914591},
{"learn":[0.4034696026],"iteration":103,"passed_time":8.234875846,"remaining_time":15.51957371},
{"learn":[0.4031223716],"iteration":104,"passed_time":8.313018175,"remaining_time":15.43846233},
{"learn":[0.4026814492],"iteration":105,"passed_time":8.384660624,"remaining_time":15.34551095},
{"learn":[0.4023722158],"iteration":106,"passed_time":8.454465565,"remaining_time":15.2496435},
{"learn":[0.4018048926],"iteration":107,"passed_time":8.538698139,"remaining_time":15.1799078},
{"learn":[0.4012686513],"iteration":108,"passed_time":8.621542456,"remaining_time":15.10747348},
{"learn":[0.4010277171],"iteration":109,"passed_time":8.688602006,"remaining_time":15.00758528},
{"learn":[0.4008108808],"iteration":110,"passed_time":8.758594193,"remaining_time":14.913282},
{"learn":[0.4002900936],"iteration":111,"passed_time":8.835501056,"remaining_time":14.83101963},
{"learn":[0.3995729437],"iteration":112,"passed_time":8.908551129,"remaining_time":14.74246957},
{"learn":[0.3992345574],"iteration":113,"passed_time":8.976808691,"remaining_time":14.64637208},
{"learn":[0.3987264236],"iteration":114,"passed_time":9.058565509,"remaining_time":14.57247495},
{"learn":[0.3981270572],"iteration":115,"passed_time":9.131032524,"remaining_time":14.48370676},
{"learn":[0.3977465587],"iteration":116,"passed_time":9.213678684,"remaining_time":14.41113845},
{"learn":[0.39731915],"iteration":117,"passed_time":9.296436282,"remaining_time":14.33857122},
{"learn":[0.3966169406],"iteration":118,"passed_time":9.385625458,"remaining_time":14.27561519},
{"learn":[0.3961898458],"iteration":119,"passed_time":9.454299245,"remaining_time":14.18144887},
{"learn":[0.3959713639],"iteration":120,"passed_time":9.518394613,"remaining_time":14.08093087},
{"learn":[0.395585797],"iteration":121,"passed_time":9.592858923,"remaining_time":13.99613843},
{"learn":[0.3952272865],"iteration":122,"passed_time":9.675243384,"remaining_time":13.92291121},
{"learn":[0.3947903397],"iteration":123,"passed_time":9.751313228,"remaining_time":13.84057361},
{"learn":[0.3943881827],"iteration":124,"passed_time":9.822527242,"remaining_time":13.75153814},
{"learn":[0.3941224135],"iteration":125,"passed_time":9.886431865,"remaining_time":13.65269162},
{"learn":[0.3936752938],"iteration":126,"passed_time":9.960972549,"remaining_time":13.56888387},
{"learn":[0.3932618676],"iteration":127,"passed_time":10.03610789,"remaining_time":13.48601998},
{"learn":[0.3928839726],"iteration":128,"passed_time":10.12339529,"remaining_time":13.41938445},
{"learn":[0.3925410363],"iteration":129,"passed_time":10.20992646,"remaining_time":13.3514423},
{"learn":[0.3922633671],"iteration":130,"passed_time":10.29519881,"remaining_time":13.28159235},
{"learn":[0.39179442],"iteration":131,"passed_time":10.38649103,"remaining_time":13.2191704},
{"learn":[0.3913562202],"iteration":132,"passed_time":10.46775772,"remaining_time":13.14372586},
{"learn":[0.3911314426],"iteration":133,"passed_time":10.54724101,"remaining_time":13.06598513},
{"learn":[0.3907510554],"iteration":134,"passed_time":10.63010278,"remaining_time":12.99234784},
{"learn":[0.3904884599],"iteration":135,"passed_time":10.702138,"remaining_time":12.90551936},
{"learn":[0.3902029611],"iteration":136,"passed_time":10.78409984,"remaining_time":12.83071732},
{"learn":[0.3899237173],"iteration":137,"passed_time":10.85181708,"remaining_time":12.73908961},
{"learn":[0.3895413259],"iteration":138,"passed_time":10.91884454,"remaining_time":12.64700698},
{"learn":[0.3891357451],"iteration":139,"passed_time":10.99651107,"remaining_time":12.56744122},
{"learn":[0.3888850538],"iteration":140,"passed_time":11.07598235,"remaining_time":12.48993754},
{"learn":[0.3887239263],"iteration":141,"passed_time":11.14317289,"remaining_time":12.39874166},
{"learn":[0.3884569621],"iteration":142,"passed_time":11.22029077,"remaining_time":12.31878078},
{"learn":[0.3882202807],"iteration":143,"passed_time":11.2914857,"remaining_time":12.23244284},
{"learn":[0.3877848398],"iteration":144,"passed_time":11.37558905,"remaining_time":12.16011243},
{"learn":[0.3874806374],"iteration":145,"passed_time":11.44238175,"remaining_time":12.06936158},
{"learn":[0.3873034904],"iteration":146,"passed_time":11.52336488,"remaining_time":11.9937063},
{"learn":[0.3868771926],"iteration":147,"passed_time":11.59711653,"remaining_time":11.91055211},
{"learn":[0.3863556336],"iteration":148,"passed_time":11.6788648,"remaining_time":11.83562808},
{"learn":[0.3859728953],"iteration":149,"passed_time":11.74586421,"remaining_time":11.74586421},
{"learn":[0.3856929206],"iteration":150,"passed_time":11.81947016,"remaining_time":11.66292089},
{"learn":[0.3855294641],"iteration":151,"passed_time":11.88242141,"remaining_time":11.5697261},
{"learn":[0.3852559096],"iteration":152,"passed_time":11.94911315,"remaining_time":11.48052047},
{"learn":[0.3847008634],"iteration":153,"passed_time":12.02087757,"remaining_time":11.3964164},
{"learn":[0.384365701],"iteration":154,"passed_time":12.08970906,"remaining_time":11.30972783},
{"learn":[0.3840352772],"iteration":155,"passed_time":12.16805586,"remaining_time":11.23205157},
{"learn":[0.3835470259],"iteration":156,"passed_time":12.2554941,"remaining_time":11.16264749},
{"learn":[0.3833612778],"iteration":157,"passed_time":12.32746426,"remaining_time":11.07911345},
{"learn":[0.3829024585],"iteration":158,"passed_time":12.41507192,"remaining_time":11.00959208},
{"learn":[0.3824959729],"iteration":159,"passed_time":12.51316825,"remaining_time":10.94902222},
{"learn":[0.3820365384],"iteration":160,"passed_time":12.59995905,"remaining_time":10.87822551},
{"learn":[0.3818084718],"iteration":161,"passed_time":12.67408581,"remaining_time":10.79644347},
{"learn":[0.3816324332],"iteration":162,"passed_time":12.75439307,"remaining_time":10.71995},
{"learn":[0.3812835379],"iteration":163,"passed_time":12.84761726,"remaining_time":10.65412163},
{"learn":[0.3808960656],"iteration":164,"passed_time":12.94151983,"remaining_time":10.58851623},
{"learn":[0.380434084],"iteration":165,"passed_time":13.02256891,"remaining_time":10.51219418},
{"learn":[0.3801939451],"iteration":166,"passed_time":13.09693832,"remaining_time":10.43049579},
{"learn":[0.3800375962],"iteration":167,"passed_time":13.1650414,"remaining_time":10.3439611},
{"learn":[0.3796667508],"iteration":168,"passed_time":13.24619463,"remaining_time":10.26776033},
{"learn":[0.379443821],"iteration":169,"passed_time":13.32178376,"remaining_time":10.18724641},
{"learn":[0.37928988],"iteration":170,"passed_time":13.39167158,"remaining_time":10.10248909},
{"learn":[0.3789512141],"iteration":171,"passed_time":13.46929781,"remaining_time":10.02366349},
{"learn":[0.3788056003],"iteration":172,"passed_time":13.53633967,"remaining_time":9.937081724},
{"learn":[0.3786802056],"iteration":173,"passed_time":13.60406763,"remaining_time":9.85122139},
{"learn":[0.3783923605],"iteration":174,"passed_time":13.68511097,"remaining_time":9.775079266},
{"learn":[0.3781169117],"iteration":175,"passed_time":13.76149044,"remaining_time":9.695595535},
{"learn":[0.3779454847],"iteration":176,"passed_time":13.83103643,"remaining_time":9.611398196},
{"learn":[0.3777911843],"iteration":177,"passed_time":13.90307323,"remaining_time":9.529072666},
{"learn":[0.3771859718],"iteration":178,"passed_time":13.98445883,"remaining_time":9.453181664},
{"learn":[0.3768858757],"iteration":179,"passed_time":14.05873902,"remaining_time":9.372492679},
{"learn":[0.3767175395],"iteration":180,"passed_time":14.12139187,"remaining_time":9.284230011},
{"learn":[0.3766173513],"iteration":181,"passed_time":14.1895954,"remaining_time":9.199847569},
{"learn":[0.3762929904],"iteration":182,"passed_time":14.26783416,"remaining_time":9.122057903},
{"learn":[0.3760066792],"iteration":183,"passed_time":14.34077159,"remaining_time":9.040921221},
{"learn":[0.3756920112],"iteration":184,"passed_time":14.41287051,"remaining_time":8.95935194},
{"learn":[0.3753859965],"iteration":185,"passed_time":14.49403473,"remaining_time":8.883440641},
{"learn":[0.375181169],"iteration":186,"passed_time":14.56155623,"remaining_time":8.799229165},
{"learn":[0.3749227252],"iteration":187,"passed_time":14.65191351,"remaining_time":8.728799535},
{"learn":[0.374633608],"iteration":188,"passed_time":14.72859436,"remaining_time":8.650126846},
{"learn":[0.3745180995],"iteration":189,"passed_time":14.79482382,"remaining_time":8.565424316},
{"learn":[0.3743815119],"iteration":190,"passed_time":14.86557372,"remaining_time":8.483494951},
{"learn":[0.3741231054],"iteration":191,"passed_time":14.95334478,"remaining_time":8.411256438},
{"learn":[0.3738115565],"iteration":192,"passed_time":15.02104664,"remaining_time":8.327730522},
{"learn":[0.3736314117],"iteration":193,"passed_time":15.09577975,"remaining_time":8.248209554},
{"learn":[0.3734696283],"iteration":194,"passed_time":15.18186595,"remaining_time":8.174850896},
{"learn":[0.3731381625],"iteration":195,"passed_time":15.26096306,"remaining_time":8.097653866},
{"learn":[0.372923223],"iteration":196,"passed_time":15.33152091,"remaining_time":8.015972863},
{"learn":[0.3727019013],"iteration":197,"passed_time":15.40023703,"remaining_time":7.933455439},
{"learn":[0.372360949],"iteration":198,"passed_time":15.49016769,"remaining_time":7.861843904},
{"learn":[0.3720427517],"iteration":199,"passed_time":15.55891259,"remaining_time":7.779456297},
{"learn":[0.3717801849],"iteration":200,"passed_time":15.63166679,"remaining_time":7.699179163},
{"learn":[0.3716257723],"iteration":201,"passed_time":15.73514858,"remaining_time":7.633883966},
{"learn":[0.3713825097],"iteration":202,"passed_time":15.83116432,"remaining_time":7.564645022},
{"learn":[0.3712270056],"iteration":203,"passed_time":15.89845972,"remaining_time":7.481628101},
{"learn":[0.3708383707],"iteration":204,"passed_time":15.98213145,"remaining_time":7.4063536},
{"learn":[0.3706639683],"iteration":205,"passed_time":16.0511309,"remaining_time":7.324302449},
{"learn":[0.3705030673],"iteration":206,"passed_time":16.12265949,"remaining_time":7.243513685},
{"learn":[0.3702595918],"iteration":207,"passed_time":16.20127608,"remaining_time":7.165949035},
{"learn":[0.3699833939],"iteration":208,"passed_time":16.28726099,"remaining_time":7.091582537},
{"learn":[0.369833628],"iteration":209,"passed_time":16.3555133,"remaining_time":7.0095057},
{"learn":[0.3694440848],"iteration":210,"passed_time":16.4280374,"remaining_time":6.929361747},
{"learn":[0.3691047532],"iteration":211,"passed_time":16.51323401,"remaining_time":6.854549968},
{"learn":[0.3688041212],"iteration":212,"passed_time":16.57993696,"remaining_time":6.772086926},
{"learn":[0.3684166507],"iteration":213,"passed_time":16.64476293,"remaining_time":6.689016877},
{"learn":[0.3680341177],"iteration":214,"passed_time":16.73263435,"remaining_time":6.615227534},
{"learn":[0.367680871],"iteration":215,"passed_time":16.82195292,"remaining_time":6.541870579},
{"learn":[0.3673436],"iteration":216,"passed_time":16.91270027,"remaining_time":6.468913007},
{"learn":[0.3670513998],"iteration":217,"passed_time":16.99414391,"remaining_time":6.392292662},
{"learn":[0.3667793318],"iteration":218,"passed_time":17.07871662,"remaining_time":6.316785598},
{"learn":[0.3665765643],"iteration":219,"passed_time":17.14880638,"remaining_time":6.235929592},
{"learn":[0.3664886561],"iteration":220,"passed_time":17.20971487,"remaining_time":6.151889024},
{"learn":[0.3662577047],"iteration":221,"passed_time":17.28178747,"remaining_time":6.071979381},
{"learn":[0.3660909913],"iteration":222,"passed_time":17.35716508,"remaining_time":5.993281215},
{"learn":[0.3658993809],"iteration":223,"passed_time":17.43320835,"remaining_time":5.914838548},
{"learn":[0.3657125094],"iteration":224,"passed_time":17.50942389,"remaining_time":5.836474628},
{"learn":[0.3654216486],"iteration":225,"passed_time":17.5808523,"remaining_time":5.756562257},
{"learn":[0.3650005442],"iteration":226,"passed_time":17.65466117,"remaining_time":5.677490156},
{"learn":[0.3648775342],"iteration":227,"passed_time":17.71712791,"remaining_time":5.594882498},
{"learn":[0.3646266065],"iteration":228,"passed_time":17.79496046,"remaining_time":5.517214815},
{"learn":[0.3644153371],"iteration":229,"passed_time":17.88127236,"remaining_time":5.442126369},
{"learn":[0.3642278953],"iteration":230,"passed_time":17.94678896,"remaining_time":5.36072917},
{"learn":[0.3637272902],"iteration":231,"passed_time":18.02819077,"remaining_time":5.284124881},
{"learn":[0.363446436],"iteration":232,"passed_time":18.10822977,"remaining_time":5.207087532},
{"learn":[0.3633095559],"iteration":233,"passed_time":18.18378085,"remaining_time":5.128758701},
{"learn":[0.3631416501],"iteration":234,"passed_time":18.25613296,"remaining_time":5.049568692},
{"learn":[0.3629467263],"iteration":235,"passed_time":18.32785731,"remaining_time":4.97026639},
{"learn":[0.3627816416],"iteration":236,"passed_time":18.40043442,"remaining_time":4.891254718},
{"learn":[0.3625235049],"iteration":237,"passed_time":18.4813872,"remaining_time":4.814479018},
{"learn":[0.3621944842],"iteration":238,"passed_time":18.55925159,"remaining_time":4.736880112},
{"learn":[0.3618579538],"iteration":239,"passed_time":18.6332693,"remaining_time":4.658317324},
{"learn":[0.3616460953],"iteration":240,"passed_time":18.7101025,"remaining_time":4.580481524},
{"learn":[0.3613182588],"iteration":241,"passed_time":18.80147604,"remaining_time":4.506138885},
{"learn":[0.3611757383],"iteration":242,"passed_time":18.87737935,"remaining_time":4.428027256},
{"learn":[0.3610097498],"iteration":243,"passed_time":18.94888622,"remaining_time":4.348924706},
{"learn":[0.3609184962],"iteration":244,"passed_time":19.01443473,"remaining_time":4.268546572},
{"learn":[0.3607418705],"iteration":245,"passed_time":19.09099383,"remaining_time":4.190705963},
{"learn":[0.3604393966],"iteration":246,"passed_time":19.16440873,"remaining_time":4.112201064},
{"learn":[0.3602312715],"iteration":247,"passed_time":19.23413225,"remaining_time":4.032963213},
{"learn":[0.3597785503],"iteration":248,"passed_time":19.31283665,"remaining_time":3.955641241},
{"learn":[0.359465535],"iteration":249,"passed_time":19.38084295,"remaining_time":3.876168591},
{"learn":[0.3592166603],"iteration":250,"passed_time":19.45753245,"remaining_time":3.79848243},
{"learn":[0.359088471],"iteration":251,"passed_time":19.53185286,"remaining_time":3.720352926},
{"learn":[0.3589816725],"iteration":252,"passed_time":19.59815613,"remaining_time":3.640764183},
{"learn":[0.3587035623],"iteration":253,"passed_time":19.67757515,"remaining_time":3.563655342},
{"learn":[0.3585325825],"iteration":254,"passed_time":19.75337789,"remaining_time":3.485890217},
{"learn":[0.3583376169],"iteration":255,"passed_time":19.81784944,"remaining_time":3.406192872},
{"learn":[0.3581619465],"iteration":256,"passed_time":19.89441745,"remaining_time":3.328637939},
{"learn":[0.3579246392],"iteration":257,"passed_time":19.96357935,"remaining_time":3.24988501},
{"learn":[0.3576810822],"iteration":258,"passed_time":20.03270713,"remaining_time":3.171200743},
{"learn":[0.3572850202],"iteration":259,"passed_time":20.10984355,"remaining_time":3.093822084},
{"learn":[0.35709625],"iteration":260,"passed_time":20.17606241,"remaining_time":3.014813924},
{"learn":[0.3569075369],"iteration":261,"passed_time":20.2443159,"remaining_time":2.936198489},
{"learn":[0.3567586523],"iteration":262,"passed_time":20.30433498,"remaining_time":2.856503401},
{"learn":[0.3565320555],"iteration":263,"passed_time":20.37593379,"remaining_time":2.778536426},
{"learn":[0.3560832538],"iteration":264,"passed_time":20.45022844,"remaining_time":2.700973568},
{"learn":[0.3556416351],"iteration":265,"passed_time":20.52655346,"remaining_time":2.623694803},
{"learn":[0.3554496072],"iteration":266,"passed_time":20.59397215,"remaining_time":2.545322401},
{"learn":[0.3552514594],"iteration":267,"passed_time":20.66884733,"remaining_time":2.467922069},
{"learn":[0.3550025578],"iteration":268,"passed_time":20.7471117,"remaining_time":2.390931088},
{"learn":[0.354832291],"iteration":269,"passed_time":20.81340391,"remaining_time":2.312600435},
{"learn":[0.3545994034],"iteration":270,"passed_time":20.88720486,"remaining_time":2.235162144},
{"learn":[0.3543651697],"iteration":271,"passed_time":20.95953149,"remaining_time":2.157598829},
{"learn":[0.354145701],"iteration":272,"passed_time":21.03379474,"remaining_time":2.080265414},
{"learn":[0.353879764],"iteration":273,"passed_time":21.11150885,"remaining_time":2.003281862},
{"learn":[0.3536288644],"iteration":274,"passed_time":21.1879467,"remaining_time":1.926176973},
{"learn":[0.3532970133],"iteration":275,"passed_time":21.2747303,"remaining_time":1.849976548},
{"learn":[0.3530635215],"iteration":276,"passed_time":21.34891994,"remaining_time":1.772654002},
{"learn":[0.3527648817],"iteration":277,"passed_time":21.43164834,"remaining_time":1.696029725},
{"learn":[0.3524968253],"iteration":278,"passed_time":21.50673233,"remaining_time":1.618786304},
{"learn":[0.3523423473],"iteration":279,"passed_time":21.58518745,"remaining_time":1.541799104},
{"learn":[0.3520261532],"iteration":280,"passed_time":21.6570499,"remaining_time":1.464355687},
{"learn":[0.3518331894],"iteration":281,"passed_time":21.726837,"remaining_time":1.386819383},
{"learn":[0.3514637775],"iteration":282,"passed_time":21.81230369,"remaining_time":1.310279727},
{"learn":[0.3510969196],"iteration":283,"passed_time":21.89364215,"remaining_time":1.233444628},
{"learn":[0.3508968799],"iteration":284,"passed_time":21.960607,"remaining_time":1.155821421},
{"learn":[0.3505209172],"iteration":285,"passed_time":22.04290744,"remaining_time":1.079023441},
{"learn":[0.3503519098],"iteration":286,"passed_time":22.12698724,"remaining_time":1.002267715},
{"learn":[0.3500321732],"iteration":287,"passed_time":22.20393403,"remaining_time":0.9251639177},
{"learn":[0.3497448737],"iteration":288,"passed_time":22.28480337,"remaining_time":0.848210509},
{"learn":[0.3493356858],"iteration":289,"passed_time":22.3639962,"remaining_time":0.7711722828},
{"learn":[0.3491944161],"iteration":290,"passed_time":22.43877907,"remaining_time":0.6939828579},
{"learn":[0.3488546025],"iteration":291,"passed_time":22.52901114,"remaining_time":0.6172331818},
{"learn":[0.348634683],"iteration":292,"passed_time":22.61894129,"remaining_time":0.5403842628},
{"learn":[0.3483218065],"iteration":293,"passed_time":22.6907831,"remaining_time":0.4630772061},
{"learn":[0.3481091036],"iteration":294,"passed_time":22.75982406,"remaining_time":0.3857597298},
{"learn":[0.3478672662],"iteration":295,"passed_time":22.82866563,"remaining_time":0.3084954815},
{"learn":[0.3476533551],"iteration":296,"passed_time":22.892654,"remaining_time":0.2312389293},
{"learn":[0.3473615134],"iteration":297,"passed_time":22.96750828,"remaining_time":0.1541443509},
{"learn":[0.3470899334],"iteration":298,"passed_time":23.05019106,"remaining_time":0.07709093999},
{"learn":[0.3468130878],"iteration":299,"passed_time":23.1277245,"remaining_time":0}
]}